README.md
setup.py
mirai_core/__init__.py
mirai_core/bot.py
mirai_core/exceptions.py
mirai_core/log.py
mirai_core/network.py
mirai_core/updater.py
mirai_core/models/Constant.py
mirai_core/models/Entity.py
mirai_core/models/Event.py
mirai_core/models/Message.py
mirai_core/models/Types.py
mirai_core/models/__init__.py
python_mirai_core.egg-info/PKG-INFO
python_mirai_core.egg-info/SOURCES.txt
python_mirai_core.egg-info/dependency_links.txt
python_mirai_core.egg-info/requires.txt
python_mirai_core.egg-info/top_level.txt